ssvd/__init__.py
ssvd/__version__.py
ssvd/core.py
ssvd-5.2.0.dist-info/DESCRIPTION.rst
ssvd-5.2.0.dist-info/METADATA
ssvd-5.2.0.dist-info/RECORD
ssvd-5.2.0.dist-info/WHEEL
ssvd-5.2.0.dist-info/metadata.json
ssvd-5.2.0.dist-info/top_level.txt
