Metadata-Version: 2.0
Name: ssvd
Version: 5.2.0
Summary: Sparse Singular Value Decomposition for biclustering.
Home-page: https://github.com/KaiWang23/SSVD
Author: Kai Wang/Yi Zhu
Author-email: kylewang06@gmail.com
License: MIT
Platform: UNKNOWN
Classifier: License :: OSI Approved :: MIT License
Classifier: Programming Language :: Python
Classifier: Programming Language :: Python :: 3
Classifier: Programming Language :: Python :: 3.6
Classifier: Programming Language :: Python :: Implementation :: CPython
Classifier: Programming Language :: Python :: Implementation :: PyPy
Requires-Python: >=3.6.0
